example/__init__.py
example/auto_register/__init__.py
example/auto_register/algorithms.py
example/auto_register/main.py
example/auto_register/main2.py
example/basic/__init__.py
example/basic/algorithms.py
example/basic/main.py
ml_platform_client/__init__.py
ml_platform_client/algorithm_base.py
ml_platform_client/algorithm_manager.py
ml_platform_client/api.py
ml_platform_client/api_util.py
ml_platform_client/base.py
ml_platform_client/config.py
ml_platform_client/constants.py
ml_platform_client/context.py
ml_platform_client/dispatcher.py
ml_platform_client/field_type.py
ml_platform_client/kafka_accessor.py
ml_platform_client/load_checker.py
ml_platform_client/logger.py
ml_platform_client/minio_accessor.py
ml_platform_client/mysql_accessor.py
ml_platform_client/node_info.py
ml_platform_client/server.py
ml_platform_client/service_response.py
ml_platform_client/setup.py
ml_platform_client/train_manager.py
ml_platform_client/util.py
ml_platform_client/worker.py
ml_platform_client/validation/__init__.py
ml_platform_client/validation/common.py
ml_platform_client/validation/exceptions.py
ml_platform_client/validation/para.py
ml_platform_client/validation/validator.py
selfcheck/__init__.py
selfcheck/algorithm_type.py
selfcheck/config.py
selfcheck/constant.py
selfcheck/minio_accessor.py
selfcheck/self_check_runner.py
selfcheck/util.py
selfcheck/executor/__init__.py
selfcheck/executor/executor.py
selfcheck/executor/load_executor.py
selfcheck/executor/predict_executor.py
selfcheck/executor/status_executor.py
selfcheck/executor/train_executor.py
selfcheck/executor/unload_executor.py
selfcheck/run_cases/__init__.py
selfcheck/run_cases/run_classify.py
selfcheck/run_cases/run_classify_act.py
selfcheck/run_cases/run_classify_fake.py
selfcheck/run_cases/run_classify_fake2.py
selfcheck/run_cases/run_cluster.py
selfcheck/run_cases/run_relation.py
selfcheck/run_cases/run_tag_cluster.py
test/__init__.py
test/worker_test.py
ml_platform_client-0.4.8.dist-info/METADATA
ml_platform_client-0.4.8.dist-info/WHEEL
ml_platform_client-0.4.8.dist-info/top_level.txt
ml_platform_client-0.4.8.dist-info/RECORD
