Metadata-Version: 2.1
Name: ml-platform-client
Version: 0.4.8
Summary: emotibot ml platform client for python
Home-page: UNKNOWN
Author: JeremyXin
Author-email: chengjiexin@emotibot.com
License: UNKNOWN
Platform: UNKNOWN
Classifier: Programming Language :: Python :: 3
Classifier: License :: OSI Approved :: MIT License
Classifier: Operating System :: OS Independent
Requires-Python: >=3.6
Requires-Dist: flask-restful
Requires-Dist: minio
Requires-Dist: pymysql
Requires-Dist: psutil
Requires-Dist: mlp-tracking (>=0.0.3)
Requires-Dist: sqlalchemy (==1.4.7)
Requires-Dist: pymysql (==0.9.3)
Requires-Dist: pymssql (==2.1.5)
Requires-Dist: psycopg2-binary (==2.9.1)
